setup.py
seeta_dataset/__init__.py
seeta_dataset/base.py
seeta_dataset/datacenter.py
seeta_dataset/readonly_dataset.py
seeta_dataset/record_type.py
seeta_dataset/writeonly_dataset.py
seeta_dataset.egg-info/PKG-INFO
seeta_dataset.egg-info/SOURCES.txt
seeta_dataset.egg-info/dependency_links.txt
seeta_dataset.egg-info/top_level.txt