Metadata-Version: 1.2
Name: seeta-dataset
Version: 0.0.8
Summary: SeeTaaS DataSet
Home-page: UNKNOWN
Maintainer-email: seetaas@seetatech.com
License: UNKNOWN
Platform: any
Classifier: Programming Language :: Python
Classifier: Operating System :: OS Independent
